LICENSE
MANIFEST.in
README.md
setup.cfg
setup.py
exist/__init__.py
exist/auth.py
exist/cli.py
exist/exceptions.py
exist/exist.py
exist.egg-info/PKG-INFO
exist.egg-info/SOURCES.txt
exist.egg-info/dependency_links.txt
exist.egg-info/entry_points.txt
exist.egg-info/requires.txt
exist.egg-info/top_level.txt
requirements/base.txt
requirements/dev.txt
requirements/test.txt