Metadata-Version: 1.0
Name: exist
Version: 0.1.9.1
Summary: Exist API client implementation
Home-page: https://github.com/mattimck/python-exist
Author: Matt McDougall
Author-email: matt@moatmedia.com.au
License: Apache 2.0
Platform: UNKNOWN
